caddo_tool/__init__.py
caddo_tool/__main__.py
caddo_tool/defaults/__init__.py
caddo_tool/defaults/evaluate/__init__.py
caddo_tool/defaults/evaluate/evaluate_all.py
caddo_tool/defaults/init_model/__init__.py
caddo_tool/defaults/preprocess/__init__.py
caddo_tool/defaults/preprocess/rewrite_preprocess.py
caddo_tool/defaults/summarize/__init__.py
caddo_tool/defaults/summarize/summarize_all.py
caddo_tool/defaults/test/__init__.py
caddo_tool/defaults/test/simple_test.py
caddo_tool/defaults/train/__init__.py
caddo_tool/defaults/train/simple_train.py
caddo_tool/modules/__init__.py
caddo_tool/modules/attributes.py
caddo_tool/modules/module_loader.py
caddo_tool/settings/__init__.py
caddo_tool/settings/settings.py
caddo_tool/settings/settings_loader.py
caddo_tool/utils/__init__.py
caddo_tool/utils/data_loader.py
caddo_tool/utils/dict_utils.py
caddo_tool-0.17.1.dist-info/LICENSE
caddo_tool-0.17.1.dist-info/METADATA
caddo_tool-0.17.1.dist-info/WHEEL
caddo_tool-0.17.1.dist-info/top_level.txt
caddo_tool-0.17.1.dist-info/RECORD
