Metadata-Version: 2.1
Name: caddo-tool
Version: 0.17.1
Summary: Benchmark Tool for CaddoBenchmark Project
Author-email: Piotr Tylczyński <piotr@ptl.cloud>, Katarzyna Kulesa <katarzyna.kulesa@kasiait.pl>
Classifier: Programming Language :: Python :: 3
Classifier: License :: OSI Approved :: MIT License
Classifier: Operating System :: OS Independent
Requires-Python: >=3.7
License-File: LICENSE
Requires-Dist: scikit-learn
Requires-Dist: caddo-file-parser
Requires-Dist: numpy
Requires-Dist: pandas
